aristoteDash/__init__.py
aristoteDash/aristote.py
aristoteDash/aristoteDash.py
aristoteDash/confFiles/aristote.md
aristoteDash-1.3.3.dist-info/METADATA
aristoteDash-1.3.3.dist-info/WHEEL
aristoteDash-1.3.3.dist-info/top_level.txt
aristoteDash-1.3.3.dist-info/RECORD
